{
  "addr": "0x140212520",
  "tool": "binary_ninja",
  "fact_id": null,
  "body": "14021252a        int32_t* i = *(arg1 + 8)\n140212531        int64_t rsi = sx.q(arg2)\n140212537        i[rsi * 2] = arg3\n14021253e        i[rsi * 2 + 1] = arg4\n140212543        int64_t rdi = sx.q(*(arg1 + 0x10))\n14021254e        if (rdi s> 0)\n140212559        int32_t* r9 = 0x428\n14021256c        int64_t r8 = 0\n14021257a        if (r8 != rsi)\n140212613        i = *(arg1 + 8)\n140212629        if (*(i + r9 - 0x428) == arg3 && *(i + r9 - 0x424) == arg4)\n14021262b        *(i + r9 - 0x428) = 0xffffffff\n140212637        *(i + r9 - 0x424) = 0\n140212643        if (r8 u<= 9)\n140212645        int64_t rax_5 = *(arg1 + 8)\n140212649        *(rax_5 + r9 - 0x50) = 0xffffffff\n140212652        *(rax_5 + r9 - 0x4c) = 0\n140212657        int64_t rax_6 = *(arg1 + 8)\n14021265b        *(r9 + rax_6) = 0xffffffff\n140212663        *(r9 + rax_6 + 4) = 0\n140212668        i = *(arg1 + 8)\n14021266c        *(i + r9 + 0x50) = 0xffffffff\n140212675        *(i + r9 + 0x54) = 0\n140212580        int32_t rdx = i[rsi * 2]\n140212585        if (rsi.d u<= 9)\n140212592        void* rcx = *(arg1 + 8) + (rsi << 3)\n140212596        int32_t rax_1 = 0\n140212599        *(rcx + 0x3d8) = rdx\n14021259f        if (rdx != 0xffffffff)\n14021259f        rax_1 = 2\n1402125a3        *(rcx + 0x3dc) = rax_1\n1402125ad        void* rcx_1 = *(arg1 + 8) + (rsi << 3)\n1402125b4        *(rcx_1 + 0x428) = rdx\n1402125ba        int32_t rax_3\n1402125ba        rax_3.b = rdx != 0xffffffff\n1402125bd        *(rcx_1 + 0x42c) = rax_3\n1402125c7        void* rcx_2 = *(arg1 + 8) + (rsi << 3)\n1402125cb        i = nullptr\n1402125ce        if (rdx != 0xffffffff)\n1402125ce        i = 3\n1402125d2        *(rcx_2 + 0x478) = rdx\n1402125d8        *(rcx_2 + 0x47c) = i.d\n1402125de        if (rdx != 0xffffffff)\n1402125e4        i = 0x50\n14021260f        while (i s< 0x3d8)\n1402125f0        int64_t rcx_3 = *(arg1 + 8)\n1402125f7        if (*(i + rcx_3) == rdx)\n1402125f9        *(i + rcx_3) = 0xffffffff\n140212600        *(i + rcx_3 + 4) = 0\n140212605        i = &i[2]\n14021267a        r8 += 1\n14021267d        r9 = &r9[2]\n140212684        do while (r8 s< rdi)\n1402126a3        return i",
  "fetched_at": "2026-04-26T17:28:23Z"
}