{
  "addr": "0x1402cb610",
  "tool": "binary_ninja",
  "fact_id": null,
  "body": "1402cb613        if (arg2 == arg3)\n1402cb613        return \n1402cb62b        int64_t* rbx_1 = arg2 + 0x38\n1402cb631        while (true)\n1402cb631        int64_t rdx = *rbx_1\n1402cb638        if (rdx u< 0x10)\n1402cb638        goto label_1402cb667\n1402cb63a        void* rcx = rbx_1[-3]\n1402cb648        if (rdx + 1 u< 0x1000)\n1402cb648        goto label_1402cb662\n1402cb64a        void* r8 = *(rcx - 8)\n1402cb65d        if (rcx - r8 - 8 u<= 0x1f)\n1402cb65f        rcx = r8\n1402cb662        label_1402cb662:\n1402cb662        j_sub_1407864b8(rcx)\n1402cb667        label_1402cb667:\n1402cb667        rbx_1[-1] = 0\n1402cb66b        *rbx_1 = 0xf\n1402cb672        rbx_1[-3].b = 0\n1402cb676        int64_t rdx_3 = rbx_1[-4]\n1402cb67e        if (rdx_3 u< 0x10)\n1402cb67e        goto label_1402cb6ad\n1402cb680        void* rcx_2 = rbx_1[-7]\n1402cb68e        if (rdx_3 + 1 u< 0x1000)\n1402cb68e        goto label_1402cb6a8\n1402cb690        void* r8_1 = *(rcx_2 - 8)\n1402cb6a3        if (rcx_2 - r8_1 - 8 u<= 0x1f)\n1402cb6a5        rcx_2 = r8_1\n1402cb6a8        label_1402cb6a8:\n1402cb6a8        j_sub_1407864b8(rcx_2)\n1402cb6ad        label_1402cb6ad:\n1402cb6ad        rbx_1[-5] = 0\n1402cb6b1        rbx_1[-4] = 0xf\n1402cb6b9        rbx_1[-7].b = 0\n1402cb6bd        rbx_1 = &rbx_1[9]\n1402cb6c8        if (&rbx_1[-7] == arg3)\n1402cb6c8        break\n1402cb6c8        continue\n1402cb6de        _invalid_parameter_noinfo_noreturn()\n1402cb6de        noreturn\n1402cb6dd        return ",
  "fetched_at": "2026-04-26T17:33:39Z"
}