{
  "addr": "0x1402066a0",
  "tool": "binary_ninja",
  "fact_id": null,
  "body": "1402066aa        int64_t r10 = sx.q(*(arg1 + 0x38))\n1402066ae        int32_t rbx = 0\n1402066b6        if (r10.d s<= 0)\n1402066b6        return \n1402066bc        int64_t r11_1 = *(arg1 + 0x30)\n1402066c0        int64_t rcx = 0\n1402066d5        while (*(r11_1 + (rcx << 3)) != arg2 || *(*(arg1 + 0x48) + (rcx << 3)) != arg3)\n1402066d7        rbx += 1\n1402066d9        rcx += 1\n1402066df        if (rcx s>= r10)\n1402066f0        return \n1402066fc        if (rbx s>= 0 && rbx s< r10.d)\n140206708        int32_t r9_2 = r10.d - rbx\n14020670b        uint64_t i_3 = zx.q(r9_2 - 1)\n14020670f        if (r9_2 != 1)\n14020671c        if ((*(arg1 + 0x3c) & 0x80000000) != 0)\n140206736        memcpy(r11_1 + (sx.q(rbx) << 3), r11_1 + ((sx.q(rbx) + 1) << 3), sx.q(i_3.d) << 3)\n140206743        if (i_3.d s> 0)\n14020674b        if (rbx s<= rbx + 1)\n14020679a        uint64_t i_2 = zx.q(i_3.d)\n14020679d        int64_t r10_1 = (sx.q(rbx) + 1) << 3\n1402067c9        uint64_t i\n1402067b0        int64_t r9_3 = *(arg1 + 0x30)\n1402067b4        int64_t r8_3 = ((0 - 1) << 3) + r10_1\n1402067b8        r10_1 += 8\n1402067c1        *(r8_3 + r9_3) = *(r10_1 + r9_3 - 8)\n1402067c5        i = i_2\n1402067c5        i_2 -= 1\n1402067c9        do while (i != 1)\n14020675d        int64_t rdx_2 = sx.q((r10 - 1).d) << 3\n140206765        int64_t r8_2 = sx.q(rbx - 1 + i_3.d) << 3\n14020678a        uint64_t i_1\n140206770        int64_t rcx_4 = *(arg1 + 0x30)\n140206774        r8_2 -= 8\n140206778        rdx_2 -= 8\n140206781        *(r8_2 + rcx_4 + 8) = *(rdx_2 + rcx_4 + 8)\n140206786        i_1 = i_3\n140206786        i_3 -= 1\n14020678a        do while (i_1 != 1)\n1402067cb        *(arg1 + 0x38) -= 1\n1402067d4        sub_1400475e0(arg1 + 0x40, rbx)\n1402067e8        return ",
  "fetched_at": "2026-04-26T17:27:54Z"
}