{
  "addr": "0x1405c42a0",
  "tool": "binary_ninja",
  "fact_id": null,
  "body": "1405c42a5        int64_t* arg_8 = arg1\n1405c42bc        int32_t* rbx = arg2\n1405c42c2        int64_t* var_80 = arg1\n1405c42c7        int64_t rdx = *arg1\n1405c42db        int64_t rax_2 = (arg1[1] - rdx) s>> 3\n1405c42df        int64_t rsi = 0x1fffffffffffffff\n1405c42ec        if (rax_2 == 0x1fffffffffffffff)\n1405c4471        sub_140022630()\n1405c4471        noreturn\n1405c42fd        int64_t rcx_2 = (arg1[2] - rdx) s>> 3\n1405c4304        uint64_t rdx_2 = rcx_2 u>> 1\n1405c4310        if (rcx_2 u<= 0x1fffffffffffffff - rdx_2)\n1405c4312        rsi = rdx_2 + rcx_2\n1405c4319        if (rsi u< rax_2 + 1)\n1405c4319        rsi = rax_2 + 1\n1405c431d        int64_t arg_10 = rsi\n1405c432b        int32_t* rax_4 = sub_140022650(arg1, rsi)\n1405c4333        int32_t* var_88 = rax_4\n1405c4338        void* result = &rax_4[((rbx - rdx) s>> 3) * 2]\n1405c433c        void* rdx_4 = result + 8\n1405c4340        void* arg_20 = rdx_4\n1405c4348        void* var_a8 = rdx_4\n1405c4350        *result = *arg3\n1405c4357        *(result + 4) = arg3[1]\n1405c435b        void* result_1 = result\n1405c4360        int64_t r8 = arg1[1]\n1405c4364        int32_t* rcx_5 = *arg1\n1405c436a        if (rbx != r8)\n1405c43b0        int32_t* var_98_1 = rcx_5\n1405c43b5        int32_t* var_60_1 = rax_4\n1405c43ba        int32_t* r8_1 = rax_4\n1405c43bd        int32_t* var_58_1 = rax_4\n1405c43c2        int64_t* var_50_1 = arg1\n1405c43ca        while (rcx_5 != rbx)\n1405c43ce        *r8_1 = *rcx_5\n1405c43d4        r8_1[1] = rcx_5[1]\n1405c43d8        r8_1 = &r8_1[2]\n1405c43dc        int32_t* var_58_2 = r8_1\n1405c43e1        rcx_5 = &rcx_5[2]\n1405c43e5        int32_t* var_98_2 = rcx_5\n1405c43ec        int32_t* var_60_2 = r8_1\n1405c43f1        int32_t* var_a8_1 = rax_4\n1405c43f6        int64_t rcx_6 = arg1[1]\n1405c43fa        int32_t* var_90_1 = rbx\n1405c43ff        void* var_48_1 = rdx_4\n1405c4407        void* var_40_1 = rdx_4\n1405c440f        int64_t* var_38_1 = arg1\n1405c441a        while (rbx != rcx_6)\n1405c441e        *rdx_4 = *rbx\n1405c4423        *(rdx_4 + 4) = rbx[1]\n1405c4426        rdx_4 += 8\n1405c442a        void* var_40_2 = rdx_4\n1405c4432        rbx = &rbx[2]\n1405c4436        int32_t* var_90_2 = rbx\n1405c443d        void* var_48_2 = rdx_4\n1405c436c        int32_t* var_a0_1 = rcx_5\n1405c4371        int32_t* var_78_1 = rax_4\n1405c4376        int32_t* rdx_5 = rax_4\n1405c4379        int32_t* var_70_1 = rdx_5\n1405c437e        int64_t* var_68_1 = arg1\n1405c4386        while (rcx_5 != r8)\n1405c438a        *rdx_5 = *rcx_5\n1405c438f        rdx_5[1] = rcx_5[1]\n1405c4392        rdx_5 = &rdx_5[2]\n1405c4396        int32_t* var_70_2 = rdx_5\n1405c439b        rcx_5 = &rcx_5[2]\n1405c439f        int32_t* var_a0_2 = rcx_5\n1405c43a6        int32_t* var_78_2 = rdx_5\n1405c4451        sub_140048410(arg1, rax_4, rax_2 + 1, rsi)\n1405c4470        return result",
  "fetched_at": "2026-04-26T17:37:34Z"
}