{
  "addr": "0x14021b410",
  "tool": "binary_ninja",
  "fact_id": null,
  "body": "14021b424        char** rsi = arg2\n14021b42a        int64_t rax = sub_14011f9c0(arg1, arg2)\n14021b440        void* var_28\n14021b440        sub_14011f570(arg1, &var_28, rsi, rax)\n14021b445        void** var_20\n14021b445        void** rbx = var_20\n14021b44d        if (rbx == 0)\n14021b461        if (*(arg1 + 0x10) == 0x492492492492492)\n14021b5a4        std::_Xruntime_error(\"unordered_map/set too long\")\n14021b5a4        noreturn\n14021b474        rbx = operator new(zx.q((&rbx[7]).d))\n14021b479        rbx[2] = 0\n14021b47d        rbx[4] = 0\n14021b481        rbx[5] = 0\n14021b488        *(rbx + 0x10) = *rsi\n14021b493        *(rbx + 0x20) = *(rsi + 0x10)\n14021b497        rsi[2] = 0\n14021b49b        rsi[3] = 0xf\n14021b4a3        *rsi = nullptr\n14021b4a5        rbx[6].b = 0\n14021b4a8        int64_t r9_1 = *(arg1 + 0x10)\n14021b4b3        int128_t zmm0_1\n14021b4b3        if (r9_1 + 1 s< 0)\n14021b4c8        zmm0_1.d = float.s((r9_1 + 1) u>> 1 | (zx.q((r9_1 + 1).d) & 1))\n14021b4cd        zmm0_1.d = zmm0_1.d f+ zmm0_1.d\n14021b4b5        zmm0_1.d = float.s(r9_1 + 1)\n14021b4d1        int64_t rcx_4 = *(arg1 + 0x38)\n14021b4db        int128_t zmm1\n14021b4db        if (rcx_4 s< 0)\n14021b4f0        zmm1.d = float.s(rcx_4 u>> 1 | (zx.q(rcx_4.d) & 1))\n14021b4f5        zmm1.d = zmm1.d f+ zmm1.d\n14021b4dd        zmm1.d = float.s(rcx_4)\n14021b4f9        zmm0_1.d = zmm0_1.d f/ zmm1.d\n14021b501        if (not(zmm0_1.d f<= *(arg1 + 4)))\n14021b506        sub_14021b810(arg1)\n14021b51a        void var_18\n14021b51a        int64_t* rax_8 = sub_14011f570(arg1, &var_18, &rbx[2], rax)\n14021b51f        r9_1 = *(arg1 + 0x10)\n14021b526        var_28.o = *rax_8\n14021b52b        void* rdx_2 = var_28\n14021b539        void*** r8_2 = *(rdx_2 + 8)\n14021b53d        *(arg1 + 0x10) = r9_1 + 1\n14021b541        *rbx = rdx_2\n14021b544        rbx[1] = r8_2\n14021b548        *r8_2 = rbx\n14021b54b        *(rdx_2 + 8) = rbx\n14021b553        int64_t rcx_8 = *(arg1 + 0x18)\n14021b55a        int64_t rax_12 = (*(arg1 + 0x30) & rax) * 2\n14021b55d        int64_t r9_3 = *(rcx_8 + (rax_12 << 3))\n14021b565        if (r9_3 == *(arg1 + 8))\n14021b567        *(rcx_8 + (rax_12 << 3)) = rbx\n14021b57f        *(rcx_8 + (rax_12 << 3) + 8) = rbx\n14021b570        if (r9_3 == rdx_2)\n14021b572        *(rcx_8 + (rax_12 << 3)) = rbx\n14021b57d        if (*(rcx_8 + (rax_12 << 3) + 8) == r8_2)\n14021b57f        *(rcx_8 + (rax_12 << 3) + 8) = rbx\n14021b59c        return &rbx[6]",
  "fetched_at": "2026-04-26T17:28:45Z"
}