{
  "addr": "0x140055650",
  "tool": "binary_ninja",
  "fact_id": null,
  "body": "140055650        int64_t rax_3 = sx.q(*(arg1 + 0x10))\n140055654        int32_t r9 = 0\n140055659        if (rax_3.d s> 0)\n14005565e        int64_t r8_1 = 0\n140055661        int32_t* rax = *(arg1 + 8)\n140055669        if (rax[0x1b].b != 0)\n14005566d        if (*rax == arg2)\n140055687        return zx.q(r9)\n14005566f        r9 += 1\n140055672        r8_1 += 1\n140055675        rax = &rax[0x1c]\n14005567c        do while (r8_1 s< rax_3)\n140055683        return 0xffffffff",
  "fetched_at": "2026-04-26T16:54:55Z"
}