{
  "addr": "0x14056c2f0",
  "tool": "binary_ninja",
  "fact_id": null,
  "body": "14056c2fa        int64_t* i = arg1[1]\n14056c305        *arg1 = &HeroClashManagerClass::`vftable'{for `HeroClashManagerInterface'}\n14056c30b        void** rbx = *i\n14056c311        while (rbx != i)\n14056c313        int64_t* rcx = rbx[2]\n14056c31a        if (rcx != 0)\n14056c324        (**rcx)(rcx, 1)\n14056c326        rbx = *rbx\n14056c329        i = arg1[1]\n14056c336        *i[1] = 0\n14056c33d        int64_t* i_3 = *i\n14056c343        if (i_3 != 0)\n14056c363        int64_t* i_1\n14056c350        i_1 = *i_3\n14056c358        j_sub_1407864b8(i_3)\n14056c35d        i_3 = i_1\n14056c363        do while (i_1 != 0)\n14056c365        int64_t* rax_3 = arg1[1]\n14056c369        *rax_3 = rax_3\n14056c36c        void* rax_4 = arg1[1]\n14056c370        *(rax_4 + 8) = rax_4\n14056c374        arg1[2] = 0\n14056c37c        int64_t* rcx_1 = arg1[1]\n14056c384        *rcx_1[1] = 0\n14056c38b        int64_t* i_4 = *rcx_1\n14056c391        if (i_4 != 0)\n14056c3a6        int64_t* i_2\n14056c393        i_2 = *i_4\n14056c39b        j_sub_1407864b8(i_4)\n14056c3a0        i_4 = i_2\n14056c3a6        do while (i_2 != 0)\n14056c3bb        return j_sub_1407864b8(arg1[1]) __tailcall",
  "fetched_at": "2026-04-26T17:34:53Z"
}