{
  "addr": "0x140756ff4",
  "tool": "binary_ninja",
  "fact_id": null,
  "body": "140757015        void var_d8\n140757015        int64_t rax_1 = __security_cookie ^ &var_d8\n14075701c        int64_t rsi\n14075701c        rsi.b = arg3\n140757022        int64_t* rax_2 = localeconv()\n14075702e        uint128_t var_58\n14075702e        int32_t* rax_3 = _Getcvt(&var_58)\n140757036        uint128_t var_90 = *rax_3\n14075703a        int128_t zmm1 = *(rax_3 + 0x10)\n140757047        uint64_t var_70 = *(rax_3 + 0x20)\n14075704c        int32_t rcx_1 = rax_3[0xa]\n140757055        *(arg1 + 0x10) = 0\n140757059        *(arg1 + 0x20) = 0\n14075705d        *(arg1 + 0x28) = 0\n140757061        void* var_98 = arg1\n140757069        _Getcvt(&var_58)\n140757071        void* const rcx_3 = &data_1407ff8a8\n140757078        if (rsi.b == 0)\n14075707a        rcx_3 = rax_2[2]\n140757089        *(arg1 + 0x10) = std::_Maklocstr<char>(rcx_3)\n14075709f        *(arg1 + 0x20) = std::_Maklocstr<wchar_t>(\"false\")\n1407570b0        int16_t* rax_6\n1407570b0        int32_t* r9\n1407570b0        rax_6, r9 = std::_Maklocstr<wchar_t>(\"true\")\n1407570b5        *(arg1 + 0x28) = rax_6\n1407570bc        int16_t result\n1407570bc        if (rsi.b == 0)\n14075712d        var_58 = var_90\n140757135        int128_t var_48_1 = zmm1\n14075713e        uint64_t var_38_1 = var_70\n140757146        int32_t var_30_1 = rcx_1\n140757155        result = std::numpunct<uint16_t,uint16_t>::_Getvals<uint16_t>(arg1, 0, rax_2, &var_58)\n1407570be        char var_a8 = 0x2e\n1407570c2        int16_t result_1 = 0\n1407570c7        int64_t var_98_1 = 0\n1407570cf        uint128_t* var_b8_1 = &var_90\n1407570e8        int32_t* r9_1 = _Mbrtowc(&result_1, &var_a8, 1, r9)\n1407570f1        *(arg1 + 0x18) = result_1\n1407570f5        var_a8 = 0x2c\n1407570f9        result_1 = 0\n1407570fe        int64_t var_98_2 = 0\n140757106        uint128_t* var_b8_2 = &var_90\n14075711a        _Mbrtowc(&result_1, &var_a8, 1, r9_1)\n14075711f        result = result_1\n140757123        *(arg1 + 0x1a) = result\n140757162        __security_check_cookie(rax_1 ^ &var_d8)\n14075717e        return result",
  "fetched_at": "2026-04-26T17:29:52Z"
}