{
  "addr": "0x140658a80",
  "tool": "binary_ninja",
  "fact_id": null,
  "body": "140658aa1        char rax = sub_14021fe20(arg2, 0, arg3, arg4)\n140658aab        void* arg_8 = arg1\n140658ad5        char rbp = rax & sub_14021ffa0(arg2, 1) & sub_1402200b0(arg2, &arg_8, 8, nullptr)\n140658ad8        char rax_3 = sub_140220030(arg2)\n140658ae5        int512_t zmm1 = sub_1401fec80(arg_8)\n140658b41        rbp = rbp & rax_3 & sub_14021ffa0(arg2, 2) & sub_1402200b0(arg2, arg1 + 0x10, 8, nullptr) & sub_140220030(arg2) & sub_14021ffa0(arg2, 3) & sub_1402200b0(arg2, arg1 + 0x18, 4, nullptr)\n140658ba3        rbp = rbp & sub_140220030(arg2) & sub_14021ffa0(arg2, 4) & sub_1402200b0(arg2, arg1 + 0x20, 8, nullptr) & sub_140220030(arg2) & sub_14021ffa0(arg2, 5) & sub_1402200b0(arg2, arg1 + 0x1c, 4, nullptr)\n140658c05        rbp = rbp & sub_140220030(arg2) & sub_14021ffa0(arg2, 6) & sub_1402200b0(arg2, arg1 + 0x28, 0xc, nullptr) & sub_140220030(arg2) & sub_14021ffa0(arg2, 7) & sub_1402200b0(arg2, arg1 + 0x34, 4, nullptr)\n140658c41        rbp = rbp & sub_140220030(arg2) & sub_14021ffa0(arg2, 8) & sub_1402200b0(arg2, arg1 + 0x38, 4, nullptr) & sub_140220030(arg2)\n140658c44        char rax_25\n140658c44        int64_t r8\n140658c44        rax_25, r8 = sub_14021feb0(arg2)\n140658c54        char rax_26\n140658c54        int64_t r8_1\n140658c54        rax_26, r8_1 = sub_14021fe20(arg2, 9, r8, zmm1)\n140658c69        int32_t i_10 = ((*(arg1 + 0x48) - *(arg1 + 0x40)) s>> 2).d\n140658c78        int64_t r14 = 0\n140658c7b        char rdi = sub_14021fe20(arg2, 0xa, r8_1, zmm1) & 1\n140658c82        if (i_10 != 0)\n140658c84        int64_t r15_1 = 0\n140658c87        uint64_t i_5 = zx.q(i_10)\n140658ccc        uint64_t i\n140658cc1        rdi = rdi & sub_14021ffa0(arg2, 3) & sub_1402200b0(arg2, *(arg1 + 0x40) + r15_1, 4, nullptr) & sub_140220030(arg2)\n140658cc4        r15_1 += 4\n140658cc8        i = i_5\n140658cc8        i_5 -= 1\n140658ccc        do while (i != 1)\n140658cd1        char rax_31\n140658cd1        int64_t r8_2\n140658cd1        rax_31, r8_2 = sub_14021feb0(arg2)\n140658ce9        int32_t i_11 = ((*(arg1 + 0x60) - *(arg1 + 0x58)) s>> 3).d\n140658cf8        char rdi_1 = sub_14021fe20(arg2, 0xb, r8_2, zmm1) & 1\n140658cff        if (i_11 != 0)\n140658d01        int64_t r15_2 = 0\n140658d04        uint64_t i_6 = zx.q(i_11)\n140658d4c        uint64_t i_1\n140658d41        rdi_1 = rdi_1 & sub_14021ffa0(arg2, 3) & sub_1402200b0(arg2, *(arg1 + 0x58) + r15_2, 8, nullptr) & sub_140220030(arg2)\n140658d44        r15_2 += 8\n140658d48        i_1 = i_6\n140658d48        i_6 -= 1\n140658d4c        do while (i_1 != 1)\n140658d51        char rax_36\n140658d51        int64_t r8_3\n140658d51        rax_36, r8_3 = sub_14021feb0(arg2)\n140658d6e        int64_t rax_37\n140658d6e        int64_t rdx_12\n140658d6e        rdx_12:rax_37 = muls.dp.q(0x2aaaaaaaaaaaaaab, *(arg1 + 0x78) - *(arg1 + 0x70))\n140658d7c        int64_t r12_5 = rdx_12 s>> 1\n140658d86        int32_t i_12 = r12_5.d + (r12_5 u>> 0x3f).d\n140658d91        char rdi_2 = sub_14021fe20(arg2, 0xc, r8_3, zmm1) & 1\n140658d98        if (i_12 != 0)\n140658d9a        int64_t r15_3 = 0\n140658d9d        uint64_t i_7 = zx.q(i_12)\n140658ddc        uint64_t i_2\n140658dd1        rdi_2 = rdi_2 & sub_14021ffa0(arg2, 3) & sub_1402200b0(arg2, *(arg1 + 0x70) + r15_3, 0xc, nullptr) & sub_140220030(arg2)\n140658dd4        r15_3 += 0xc\n140658dd8        i_2 = i_7\n140658dd8        i_7 -= 1\n140658ddc        do while (i_2 != 1)\n140658de1        char rax_44\n140658de1        int64_t r8_4\n140658de1        rax_44, r8_4 = sub_14021feb0(arg2)\n140658dff        int32_t i_13 = ((*(arg1 + 0x90) - *(arg1 + 0x88)) s>> 2).d\n140658e0e        char rdi_3 = sub_14021fe20(arg2, 0xd, r8_4, zmm1) & 1\n140658e15        if (i_13 != 0)\n140658e17        int64_t r15_4 = 0\n140658e1a        uint64_t i_8 = zx.q(i_13)\n140658e5f        uint64_t i_3\n140658e54        rdi_3 = rdi_3 & sub_14021ffa0(arg2, 3) & sub_1402200b0(arg2, *(arg1 + 0x88) + r15_4, 4, nullptr) & sub_140220030(arg2)\n140658e57        r15_4 += 4\n140658e5b        i_3 = i_8\n140658e5b        i_8 -= 1\n140658e5f        do while (i_3 != 1)\n140658e64        char rax_49\n140658e64        int64_t r8_5\n140658e64        rax_49, r8_5 = sub_14021feb0(arg2)\n140658e82        int32_t i_14 = ((*(arg1 + 0xa8) - *(arg1 + 0xa0)) s>> 2).d\n140658e91        char rdi_4 = sub_14021fe20(arg2, 0xe, r8_5, zmm1) & 1\n140658e98        if (i_14 != 0)\n140658e9a        uint64_t i_9 = zx.q(i_14)\n140658edf        uint64_t i_4\n140658ed4        rdi_4 = rdi_4 & sub_14021ffa0(arg2, 3) & sub_1402200b0(arg2, *(arg1 + 0xa0) + r14, 4, nullptr) & sub_140220030(arg2)\n140658ed7        r14 += 4\n140658edb        i_4 = i_9\n140658edb        i_9 -= 1\n140658edf        do while (i_4 != 1)\n140658eec        rdi_4 &= sub_14021feb0(arg2)\n140658f10        return sub_14021feb0(arg2) & rdi_4 & rbp & rax_25 & rax_26 & rax_31 & rdi & rax_36 & rdi_1 & rax_44 & rdi_2 & rax_49 & rdi_3",
  "fetched_at": "2026-04-26T17:07:00Z"
}