{
  "cases": [
    {
      "name": "roe-steammod",
      "processName": "StarWarsG",
      "processPath": "D:/SteamLibrary/steamapps/common/Star Wars Empire at War/corruption/StarWarsG.exe",
      "commandLine": "StarWarsG.exe STEAMMOD=3447786229"
    },
    {
      "name": "aotr-steammod",
      "processName": "StarWarsG",
      "processPath": "D:/SteamLibrary/steamapps/common/Star Wars Empire at War/corruption/StarWarsG.exe",
      "commandLine": "StarWarsG.exe STEAMMOD=1397421866"
    },
    {
      "name": "roe-modpath",
      "processName": "StarWarsG",
      "processPath": "D:/SteamLibrary/steamapps/common/Star Wars Empire at War/corruption/StarWarsG.exe",
      "commandLine": "StarWarsG.exe MODPATH=\"D:/mods/3447786229(submod)\""
    },
    {
      "name": "aotr-modpath",
      "processName": "StarWarsG",
      "processPath": "D:/SteamLibrary/steamapps/common/Star Wars Empire at War/corruption/StarWarsG.exe",
      "commandLine": "StarWarsG.exe MODPATH=Mods\\AOTR"
    },
    {
      "name": "sweaw-base",
      "processName": "sweaw",
      "processPath": "D:/SteamLibrary/steamapps/common/Star Wars Empire at War/GameData/sweaw.exe",
      "commandLine": "sweaw.exe"
    },
    {
      "name": "starwarsg-no-cmd",
      "processName": "StarWarsG",
      "processPath": "D:/SteamLibrary/steamapps/common/Star Wars Empire at War/corruption/StarWarsG.exe",
      "commandLine": null
    },
    {
      "name": "mixed-steammod-aotr-modpath-roe",
      "processName": "StarWarsG",
      "processPath": "D:/SteamLibrary/steamapps/common/Star Wars Empire at War/corruption/StarWarsG.exe",
      "commandLine": "StarWarsG.exe STEAMMOD=1397421866 MODPATH=\"D:/mods/3447786229(submod)\""
    },
    {
      "name": "mixed-steammod-roe-modpath-aotr",
      "processName": "StarWarsG",
      "processPath": "D:/SteamLibrary/steamapps/common/Star Wars Empire at War/corruption/StarWarsG.exe",
      "commandLine": "StarWarsG.exe STEAMMOD=3447786229 MODPATH=Mods\\AOTR"
    },
    {
      "name": "aotr-modpath-spaces",
      "processName": "StarWarsG",
      "processPath": "D:/SteamLibrary/steamapps/common/Star Wars Empire at War/corruption/StarWarsG.exe",
      "commandLine": "StarWarsG.exe MODPATH=\"C:/Mod Library/Awakening of the Rebellion\""
    },
    {
      "name": "roe-modpath-order66",
      "processName": "StarWarsG",
      "processPath": "D:/SteamLibrary/steamapps/common/Star Wars Empire at War/corruption/StarWarsG.exe",
      "commandLine": "StarWarsG.exe MODPATH=\"C:/mods/Order 66 Submod\""
    },
    {
      "name": "swfoc-base-no-mod",
      "processName": "swfoc",
      "processPath": "D:/SteamLibrary/steamapps/common/Star Wars Empire at War/corruption/swfoc.exe",
      "commandLine": "swfoc.exe"
    }
  ]
}
