{
  "addr": "0x14076ff68",
  "tool": "ghidra",
  "fact_id": null,
  "body": "/* Library Function - Single Match\n    private: void __cdecl FH4::HandlerMap4::DecompHandler(void) __ptr64\n   \n   Library: Visual Studio 2019 Release */\n\nvoid __thiscall FH4::HandlerMap4::DecompHandler(HandlerMap4 *this)\n\n{\n  HandlerMap4 HVar1;\n  HandlerMap4 HVar2;\n  undefined4 uVar3;\n  int iVar4;\n  uint uVar5;\n  byte bVar6;\n  ulonglong uVar7;\n  HandlerMap4 *pHVar8;\n  HandlerMap4 *pHVar9;\n  \n  this[0x18] = (HandlerMap4)0x0;\n  *(undefined8 *)(this + 0x1c) = 0;\n  *(undefined8 *)(this + 0x24) = 0;\n  *(undefined8 *)(this + 0x30) = 0;\n  *(undefined8 *)(this + 0x38) = 0;\n  HVar1 = **(HandlerMap4 **)(this + 8);\n  pHVar8 = *(HandlerMap4 **)(this + 8) + 1;\n  this[0x18] = HVar1;\n  *(HandlerMap4 **)(this + 8) = pHVar8;\n  if (((byte)HVar1 & 1) != 0) {\n    HVar2 = *pHVar8;\n    pHVar8 = pHVar8 + -(longlong)(char)(&DAT_1408d0c38)[(byte)HVar2 & 0xf];\n    *(uint *)(this + 0x1c) = *(uint *)(pHVar8 + -4) >> ((&DAT_1408d0c48)[(byte)HVar2 & 0xf] & 0x1f);\n    *(HandlerMap4 **)(this + 8) = pHVar8;\n  }\n  if (((byte)HVar1 & 2) != 0) {\n    uVar3 = *(undefined4 *)pHVar8;\n    pHVar8 = pHVar8 + 4;\n    *(HandlerMap4 **)(this + 8) = pHVar8;\n    *(undefined4 *)(this + 0x20) = uVar3;\n  }\n  if (((byte)HVar1 & 4) != 0) {\n    HVar2 = *pHVar8;\n    pHVar8 = pHVar8 + -(longlong)(char)(&DAT_1408d0c38)[(byte)HVar2 & 0xf];\n    *(uint *)(this + 0x24) = *(uint *)(pHVar8 + -4) >> ((&DAT_1408d0c48)[(byte)HVar2 & 0xf] & 0x1f);\n    *(HandlerMap4 **)(this + 8) = pHVar8;\n  }\n  pHVar9 = pHVar8 + 4;\n  *(undefined4 *)(this + 0x28) = *(undefined4 *)pHVar8;\n  bVar6 = (byte)HVar1 & 0x30;\n  *(HandlerMap4 **)(this + 8) = pHVar9;\n  if (((byte)HVar1 & 8) == 0) {\n    if (bVar6 == 0x10) {\n      bVar6 = (&DAT_1408d0c48)[(byte)*pHVar9 & 0xf];\n      uVar5 = *(uint *)(((longlong)pHVar9 - (longlong)(char)(&DAT_1408d0c38)[(byte)*pHVar9 & 0xf]) +\n                       -4);\n      *(longlong *)(this + 8) =\n           (longlong)pHVar9 - (longlong)(char)(&DAT_1408d0c38)[(byte)*pHVar9 & 0xf];\n      *(ulonglong *)(this + 0x30) = (ulonglong)(*(int *)(this + 0x48) + (uVar5 >> (bVar6 & 0x1f)));\n      return;\n    }\n    if (bVar6 != 0x20) {\n      return;\n    }\n    bVar6 = (&DAT_1408d0c48)[(byte)*pHVar9 & 0xf];\n    pHVar9 = pHVar9 + -(longlong)(char)(&DAT_1408d0c38)[(byte)*pHVar9 & 0xf];\n    uVar5 = *(uint *)(pHVar9 + -4);\n    *(HandlerMap4 **)(this + 8) = pHVar9;\n    *(ulonglong *)(this + 0x30) = (ulonglong)(*(int *)(this + 0x48) + (uVar5 >> (bVar6 & 0x1f)));\n    bVar6 = (&DAT_1408d0c48)[(byte)*pHVar9 & 0xf];\n    uVar5 = *(uint *)(((longlong)pHVar9 - (longlong)(char)(&DAT_1408d0c38)[(byte)*pHVar9 & 0xf]) +\n                     -4);\n    *(longlong *)(this + 8) =\n         (longlong)pHVar9 - (longlong)(char)(&DAT_1408d0c38)[(byte)*pHVar9 & 0xf];\n    uVar7 = (ulonglong)(*(int *)(this + 0x48) + (uVar5 >> (bVar6 & 0x1f)));\n  }\n  else {\n    if (bVar6 == 0x10) {\n      iVar4 = *(int *)pHVar9;\n      *(HandlerMap4 **)(this + 8) = pHVar8 + 8;\n      *(longlong *)(this + 0x30) = (longlong)iVar4;\n      return;\n    }\n    if (bVar6 != 0x20) {\n      return;\n    }\n    iVar4 = *(int *)pHVar9;\n    *(HandlerMap4 **)(this + 8) = pHVar8 + 8;\n    *(longlong *)(this + 0x30) = (longlong)iVar4;\n    uVar7 = (ulonglong)*(int *)(pHVar8 + 8);\n    *(HandlerMap4 **)(this + 8) = pHVar8 + 0xc;\n  }\n  *(ulonglong *)(this + 0x38) = uVar7;\n  return;\n}",
  "fetched_at": "2026-04-26T18:11:36Z"
}