{
  "addr": "0x14060c010",
  "tool": "ghidra",
  "fact_id": null,
  "body": "bool FUN_14060c010(longlong *param_1,longlong *param_2,longlong *param_3)\n\n{\n  double dVar1;\n  double dVar2;\n  undefined4 uVar3;\n  double dVar4;\n  bool bVar5;\n  ulonglong uVar6;\n  uint uVar7;\n  longlong lVar8;\n  longlong lVar9;\n  bool bVar10;\n  \n  if ((param_1[0x16] == 0) || (param_1[0x2e] != 0)) {\n    if ((param_1[0x2d] != 0) && (param_1[0x17] == 0)) {\n      uVar3 = (undefined4)param_1[0x10];\n      goto LAB_14060c05e;\n    }\n  }\n  else {\n    uVar3 = (undefined4)param_1[0x27];\nLAB_14060c05e:\n    (**(code **)(*param_1 + 0x28))(param_1,uVar3);\n  }\n  if (*(char *)((longlong)param_1 + 10) != '\\0') {\n    return (int)param_1[2] == (int)param_1[0x10];\n  }\n  lVar8 = param_2[1] - *param_2;\n  lVar8 = lVar8 / 6 + (lVar8 >> 0x3f);\n  dVar4 = 0.0;\n  bVar10 = false;\n  uVar7 = 0;\n  lVar9 = lVar8 >> 2;\n  lVar8 = lVar8 >> 0x3f;\n  if (lVar9 != lVar8) {\n    uVar6 = 0;\n    dVar4 = 0.0;\n    do {\n      dVar1 = *(double *)(*param_2 + 8 + uVar6 * 0x18);\n      if (0.0 < dVar1) {\n        bVar10 = true;\n        dVar4 = dVar4 + dVar1;\n      }\n      uVar7 = uVar7 + 1;\n      uVar6 = (ulonglong)uVar7;\n    } while (uVar6 < (ulonglong)(lVar9 - lVar8));\n  }\n  bVar5 = false;\n  lVar8 = param_3[1] - *param_3;\n  dVar1 = 0.0;\n  lVar8 = lVar8 / 6 + (lVar8 >> 0x3f);\n  uVar7 = 0;\n  lVar9 = lVar8 >> 2;\n  lVar8 = lVar8 >> 0x3f;\n  if (lVar9 != lVar8) {\n    uVar6 = 0;\n    dVar1 = 0.0;\n    bVar5 = false;\n    do {\n      dVar2 = *(double *)(*param_3 + 8 + uVar6 * 0x18);\n      if (0.0 < dVar2) {\n        bVar5 = true;\n        dVar1 = dVar1 + dVar2;\n      }\n      uVar7 = uVar7 + 1;\n      uVar6 = (ulonglong)uVar7;\n    } while (uVar6 < (ulonglong)(lVar9 - lVar8));\n  }\n  if (bVar10) {\n    if (bVar5) {\n      lVar8 = FUN_140294bc0(&DAT_140a16fd0,(int)param_1[0x10]);\n      lVar9 = FUN_140294bc0(&DAT_140a16fd0,(int)param_1[0x27]);\n      if ((((lVar8 != 0) && (*(char *)(lVar8 + 0x62) == '\\0')) && (lVar9 != 0)) &&\n         (*(char *)(lVar9 + 0x62) == '\\0')) {\n        if (*(char *)(*(longlong *)(lVar8 + 0x68) + 0x20a8) == '\\0') {\n          return true;\n        }\n        if (*(char *)(*(longlong *)(lVar9 + 0x68) + 0x20a8) == '\\0') {\n          return false;\n        }\n      }\n    }\n    else {\nLAB_14060c1cc:\n      if (dVar4 == dVar1) goto LAB_14060c1d4;\n    }\n    bVar10 = dVar4 <= dVar1;\n  }\n  else {\n    if (bVar5) goto LAB_14060c1cc;\nLAB_14060c1d4:\n    bVar10 = *(int *)((longlong)param_1 + 0xc) != (int)param_1[0x10];\n  }\n  return bVar10;\n}",
  "fetched_at": "2026-04-26T17:26:07Z"
}