{
  "addr": "0x14033f930",
  "tool": "ghidra",
  "fact_id": null,
  "body": "\nRetreatCoordinatorClass * __thiscall\nRetreatCoordinatorClass::RetreatCoordinatorClass(RetreatCoordinatorClass *this)\n\n{\n  undefined1 *puVar1;\n  uint *puVar2;\n  longlong lVar3;\n  LPVOID lpMem;\n  HANDLE hHeap;\n  \n  (this->RefCountClass_data).offset_0x8 = (undefined **)0xffffffffffffffff;\n  *(undefined4 *)&(this->RefCountClass_data).offset_0x0 = 0;\n                    /* inlined constructor or destructor (approx location) for\n                       RetreatCoordinatorClass */\n  *(undefined8 *)&(this->RefCountClass_data).field_0x28 = 0;\n  *(undefined8 *)&(this->RefCountClass_data).field_0x30 = 0;\n  this->vftablePtr = &vftable;\n  this->vftablePtr = &vftable;\n                    /* inlined constructor or destructor (approx location) for\n                       DynamicVectorClass<class_GameObjectClass*___ptr64> */\n  *(DynamicVectorClass<class_GameObjectClass*___ptr64>_vftable **)\n   &(this->RefCountClass_data).field_0x20 =\n       &::DynamicVectorClass<class_GameObjectClass*___ptr64>::vftable;\n  (this->RefCountClass_data).offset_0x10 = 0;\n  *(undefined4 *)&(this->RefCountClass_data).offset_0x18 = 0;\n  *(DynamicVectorClass<class_GameObjectClass*___ptr64>_vftable **)\n   &(this->RefCountClass_data).field_0x38 =\n       &::DynamicVectorClass<class_GameObjectClass*___ptr64>::vftable;\n  (this->RefCountClass_data).offset_0x40 = 0;\n  (this->RefCountClass_data).offset_0x48 = 0;\n  *(undefined4 *)&(this->RefCountClass_data).offset_0x50 = 0;\n  (this->RefCountClass_data).offset_0x58 = 0;\n  (this->RefCountClass_data).offset_0x60 = 0;\n  *(undefined4 *)&(this->RefCountClass_data).offset_0x68 = 0;\n  *(undefined2 *)((longlong)&(this->RefCountClass_data).offset_0x68 + 4) = 0;\n  *(undefined1 *)((longlong)&(this->RefCountClass_data).offset_0x68 + 6) = 0;\n  (this->RefCountClass_data).offset_0x70 = 0;\n  lVar3 = *(longlong *)&(this->RefCountClass_data).field_0x28;\n  if (lVar3 != 0) {\n    thunk_FUN_1407864b8(lVar3);\n    puVar1 = &(this->RefCountClass_data).field_0x34;\n    *(uint *)puVar1 = *(uint *)puVar1 & 0x80000000;\n    *(undefined8 *)&(this->RefCountClass_data).field_0x28 = 0;\n    *(undefined4 *)&(this->RefCountClass_data).field_0x30 = 0;\n  }\n  lpMem = (LPVOID)(this->RefCountClass_data).offset_0x40;\n  if (lpMem != (LPVOID)0x0) {\n    if ((*(uint *)((longlong)&(this->RefCountClass_data).offset_0x48 + 4) & 0x80000000) == 0) {\n      thunk_FUN_1407864b8(lpMem);\n    }\n    else {\n      hHeap = GetProcessHeap();\n      HeapFree(hHeap,0,lpMem);\n    }\n    puVar2 = (uint *)((longlong)&(this->RefCountClass_data).offset_0x48 + 4);\n    *puVar2 = *puVar2 & 0x80000000;\n    (this->RefCountClass_data).offset_0x40 = 0;\n    *(undefined4 *)&(this->RefCountClass_data).offset_0x48 = 0;\n  }\n  return this;\n}\n\n",
  "fetched_at": "2026-04-26T17:04:55Z"
}