{
  "addr": "0x14060e0a0",
  "tool": "ghidra",
  "fact_id": null,
  "body": "longlong FUN_14060e0a0(longlong *param_1,longlong param_2,undefined1 param_3)\n\n{\n  longlong lVar1;\n  longlong lVar2;\n  longlong lVar3;\n  undefined8 uVar4;\n  longlong lVar5;\n  longlong *plVar6;\n  longlong local_38;\n  char local_30;\n  longlong *local_28;\n  longlong local_20;\n  undefined8 local_18;\n  \n  if (param_2 == 0) {\n    lVar1 = FUN_14060e240(0x810);\n    plVar6 = *(longlong **)(lVar1 + 0x38);\n    if (plVar6 != param_1) {\n      if (plVar6 != (longlong *)0x0) {\n        (**(code **)(*plVar6 + 8))();\n      }\n      *(longlong **)(lVar1 + 0x38) = param_1;\n      if (param_1 == (longlong *)0x0) goto LAB_14060e213;\n      (**(code **)*param_1)(param_1);\n      plVar6 = *(longlong **)(lVar1 + 0x38);\n    }\n    if (plVar6 != (longlong *)0x0) {\n      lVar5 = (**(code **)(*plVar6 + 0x30))();\n      if (lVar5 != 0) {\n        lVar5 = 0;\n        lVar2 = lVar1 + 0x28;\n        if (lVar1 == 0) {\n          lVar2 = lVar5;\n        }\n        lVar3 = (**(code **)(**(longlong **)(lVar1 + 0x38) + 0x30))();\n        if (lVar3 != 0) {\n          lVar5 = lVar3 + 0x38;\n        }\n        uVar4 = FUN_140058570();\n        FUN_140220e90(uVar4,lVar5,lVar2,0x10);\n      }\n    }\n    goto LAB_14060e213;\n  }\n  lVar5 = 0;\n  local_18 = 0;\n  local_28 = param_1;\n  local_20 = param_2;\n  FUN_140257870(DAT_140b39830,&local_38,&local_28);\n  if (local_30 == '\\0') {\n    lVar1 = *(longlong *)(local_38 + 0x20);\n    goto LAB_14060e213;\n  }\n  lVar1 = FUN_14060e240(0x810);\n  plVar6 = *(longlong **)(lVar1 + 0x38);\n  if (plVar6 == param_1) {\nLAB_14060e12f:\n    if (plVar6 != (longlong *)0x0) {\n      lVar2 = (**(code **)(*plVar6 + 0x30))();\n      if (lVar2 != 0) {\n        lVar2 = lVar1 + 0x28;\n        if (lVar1 == 0) {\n          lVar2 = lVar5;\n        }\n        lVar3 = (**(code **)(**(longlong **)(lVar1 + 0x38) + 0x30))();\n        if (lVar3 != 0) {\n          lVar5 = lVar3 + 0x38;\n        }\n        uVar4 = FUN_140058570();\n        FUN_140220e90(uVar4,lVar5,lVar2,0x10);\n      }\n    }\n  }\n  else {\n    if (plVar6 != (longlong *)0x0) {\n      (**(code **)(*plVar6 + 8))();\n    }\n    *(longlong **)(lVar1 + 0x38) = param_1;\n    if (param_1 != (longlong *)0x0) {\n      (**(code **)*param_1)(param_1);\n      plVar6 = *(longlong **)(lVar1 + 0x38);\n      goto LAB_14060e12f;\n    }\n  }\n  *(longlong *)(local_38 + 0x20) = lVar1;\n  *(longlong *)(lVar1 + 0x40) = param_2;\nLAB_14060e213:\n  *(undefined1 *)(lVar1 + 0x48) = param_3;\n  return lVar1;\n}",
  "fetched_at": "2026-04-26T17:26:41Z"
}