{
  "addr": "0x140787358",
  "tool": "ghidra",
  "fact_id": null,
  "body": "/* Library Function - Multiple Matches With Same Base Name\n    double __cdecl common_strtod_l<double,char>(char const * __ptr64 const,char * __ptr64 * __ptr64\n   const,struct __crt_locale_pointers * __ptr64 const)\n    double __cdecl common_strtod_l<double,wchar_t>(wchar_t const * __ptr64 const,wchar_t * __ptr64 *\n   __ptr64 const,struct __crt_locale_pointers * __ptr64 const)\n   \n   Libraries: Visual Studio 2017 Release, Visual Studio 2019 Release */\n\nundefined8 common_strtod_l<>(longlong param_1,longlong *param_2,__crt_locale_pointers *param_3)\n\n{\n  SLD_STATUS SVar1;\n  ulong *puVar2;\n  undefined8 local_res8;\n  longlong local_38;\n  longlong *local_30;\n  longlong local_28;\n  undefined1 local_20 [16];\n  char local_10;\n  \n  if (param_2 != (longlong *)0x0) {\n    *param_2 = param_1;\n  }\n  if (param_1 == 0) {\n    puVar2 = __doserrno();\n    *puVar2 = 0x16;\n    FUN_1407711ac();\n    local_res8 = 0;\n  }\n  else {\n    _LocaleUpdate::_LocaleUpdate((_LocaleUpdate *)&local_28,param_3);\n    local_res8 = 0;\n    if (param_2 != (longlong *)0x0) {\n      *param_2 = param_1;\n    }\n    local_38 = param_1;\n    local_30 = param_2;\n    SVar1 = __crt_strtox::\n            parse_floating_point<class___crt_strtox::c_string_character_source<char>,double>\n                      (local_20,&local_38,&local_res8);\n    if (SVar1 - 2 < 2) {\n      puVar2 = __doserrno();\n      *puVar2 = 0x22;\n    }\n    if (local_10 != '\\0') {\n      *(uint *)(local_28 + 0x3a8) = *(uint *)(local_28 + 0x3a8) & 0xfffffffd;\n    }\n  }\n  return local_res8;\n}",
  "fetched_at": "2026-04-26T18:51:43Z"
}