{
  "addr": "0x14069d630",
  "tool": "ghidra",
  "fact_id": null,
  "body": "byte __thiscall\nMarkupBlockStatus::vfunction16(MarkupBlockStatus *this,undefined8 param_1,undefined8 param_2)\n\n{\n  longlong *plVar1;\n  char cVar2;\n  byte bVar3;\n  byte bVar4;\n  int iVar5;\n  MarkupBlockStatus_vftable1 **ppMVar6;\n  byte bVar7;\n  undefined8 local_res20;\n  longlong local_38 [2];\n  \n  bVar7 = 1;\n  cVar2 = FUN_1402204a0(param_2);\n  if (cVar2 != '\\0') {\n    do {\n      iVar5 = FUN_1402205a0(param_2);\n      if (iVar5 == 0) {\n        bVar3 = BlockingStatus::vfunction16((BlockingStatus *)this,param_1,param_2);\n        bVar7 = bVar7 & bVar3;\n      }\n      else if (iVar5 == 1) {\n        cVar2 = FUN_1402204a0(param_2);\n        while (cVar2 != '\\0') {\n          iVar5 = FUN_1402205a0(param_2);\n          if (iVar5 == 2) {\n            this->offset_0x48 = this->offset_0x40;\n            bVar3 = 1;\n            cVar2 = FUN_140220610(param_2);\n            if (cVar2 == '\\0') {\nLAB_14069d7c6:\n              ppMVar6 = (MarkupBlockStatus_vftable1 **)0x0;\n              if ((longlong)(this->offset_0x48 - this->offset_0x40) >> 3 != 0) {\n                do {\n                  FUN_1401fe4a0(this->offset_0x40 + (longlong)ppMVar6 * 8,\n                                *(undefined8 *)(this->offset_0x40 + (longlong)ppMVar6 * 8),0);\n                  ppMVar6 = (MarkupBlockStatus_vftable1 **)(ulonglong)((int)ppMVar6 + 1);\n                } while (ppMVar6 < (undefined1 *)\n                                   ((longlong)(this->offset_0x48 - this->offset_0x40) >> 3));\n              }\n            }\n            else {\n              do {\n                iVar5 = FUN_140220710(param_2);\n                if (iVar5 == 3) {\n                  bVar4 = FUN_140220730(param_2,local_38,8,0);\n                  bVar3 = bVar3 & bVar4;\n                  if (bVar3 != 0) {\n                    plVar1 = (longlong *)this->offset_0x48;\n                    if (plVar1 == this->offset_0x50) {\n                      FUN_14001ded0(&this->offset_0x40,plVar1,local_38);\n                    }\n                    else {\n                      *plVar1 = local_38[0];\n                      this->offset_0x48 = this->offset_0x48 + 8;\n                    }\n                  }\n                }\n                FUN_1402206a0(param_2);\n                cVar2 = FUN_140220610(param_2);\n              } while (cVar2 != '\\0');\n              if (bVar3 != 0) goto LAB_14069d7c6;\n            }\n            bVar7 = bVar7 & bVar3;\n          }\n          else if (iVar5 == 3) {\n            cVar2 = FUN_140220610(param_2);\n            while (cVar2 != '\\0') {\n              iVar5 = FUN_140220710(param_2);\n              if (iVar5 == 4) {\n                FUN_140220730(param_2,&this->field_0x40);\n              }\n              else if (iVar5 == 5) {\n                local_res20 = 0;\n                bVar3 = FUN_140220730(param_2,&local_res20);\n                bVar7 = bVar7 & bVar3;\n                ppMVar6 = &this->vftablePtr;\n                if (this == (MarkupBlockStatus *)0x0) {\n                  ppMVar6 = (MarkupBlockStatus_vftable1 **)0x0;\n                }\n                FUN_1401fe2d0(local_res20,ppMVar6);\n              }\n              else {\n                bVar7 = 0;\n              }\n              FUN_1402206a0(param_2);\n              cVar2 = FUN_140220610(param_2);\n            }\n          }\n          else {\n            bVar7 = 0;\n          }\n          FUN_140220520(param_2);\n          cVar2 = FUN_1402204a0(param_2);\n        }\n      }\n      else {\n        bVar7 = 0;\n      }\n      FUN_140220520(param_2);\n      cVar2 = FUN_1402204a0(param_2);\n    } while (cVar2 != '\\0');\n  }\n  return bVar7;\n}",
  "fetched_at": "2026-04-26T17:20:59Z"
}